<annotation>
	<folder>data</folder>
	<filename>00232.jpg</filename>
	<path>/home/wu/PycharmProjects/hat/data/00232.jpg</path>
	<source>
		<database>Unknown</database>
	</source>
	<size>
		<width>680</width>
		<height>439</height>
		<depth>3</depth>
	</size>
	<segmented>0</segmented>
	<object>
		<name>blue</name>
		<pose>Unspecified</pose>
		<truncated>0</truncated>
		<difficult>0</difficult>
		<bndbox>
			<xmin>393</xmin>
			<ymin>45</ymin>
			<xmax>538</xmax>
			<ymax>210</ymax>
		</bndbox>
	</object>
	<object>
		<name>blue</name>
		<pose>Unspecified</pose>
		<truncated>0</truncated>
		<difficult>0</difficult>
		<bndbox>
			<xmin>345</xmin>
			<ymin>145</ymin>
			<xmax>396</xmax>
			<ymax>204</ymax>
		</bndbox>
	</object>
	<object>
		<name>blue</name>
		<pose>Unspecified</pose>
		<truncated>0</truncated>
		<difficult>0</difficult>
		<bndbox>
			<xmin>121</xmin>
			<ymin>133</ymin>
			<xmax>173</xmax>
			<ymax>192</ymax>
		</bndbox>
	</object>
</annotation>
