<annotation>
	<folder>save</folder>
	<filename>00777.jpg</filename>
	<path>/home/wu/PycharmProjects/hat/save/00777.jpg</path>
	<source>
		<database>Unknown</database>
	</source>
	<size>
		<width>511</width>
		<height>383</height>
		<depth>3</depth>
	</size>
	<segmented>0</segmented>
	<object>
		<name>none</name>
		<pose>Unspecified</pose>
		<truncated>0</truncated>
		<difficult>0</difficult>
		<bndbox>
			<xmin>304</xmin>
			<ymin>218</ymin>
			<xmax>326</xmax>
			<ymax>246</ymax>
		</bndbox>
	</object>
	<object>
		<name>none</name>
		<pose>Unspecified</pose>
		<truncated>0</truncated>
		<difficult>0</difficult>
		<bndbox>
			<xmin>267</xmin>
			<ymin>210</ymin>
			<xmax>290</xmax>
			<ymax>235</ymax>
		</bndbox>
	</object>
	<object>
		<name>none</name>
		<pose>Unspecified</pose>
		<truncated>0</truncated>
		<difficult>0</difficult>
		<bndbox>
			<xmin>394</xmin>
			<ymin>195</ymin>
			<xmax>426</xmax>
			<ymax>235</ymax>
		</bndbox>
	</object>
</annotation>
