<annotation>
	<folder>save</folder>
	<filename>01048.jpg</filename>
	<path>/home/wu/PycharmProjects/hat/save/01048.jpg</path>
	<source>
		<database>Unknown</database>
	</source>
	<size>
		<width>3058</width>
		<height>2039</height>
		<depth>3</depth>
	</size>
	<segmented>0</segmented>
	<object>
		<name>red</name>
		<pose>Unspecified</pose>
		<truncated>0</truncated>
		<difficult>0</difficult>
		<bndbox>
			<xmin>751</xmin>
			<ymin>642</ymin>
			<xmax>1019</xmax>
			<ymax>994</ymax>
		</bndbox>
	</object>
	<object>
		<name>white</name>
		<pose>Unspecified</pose>
		<truncated>0</truncated>
		<difficult>0</difficult>
		<bndbox>
			<xmin>1449</xmin>
			<ymin>752</ymin>
			<xmax>1679</xmax>
			<ymax>1007</ymax>
		</bndbox>
	</object>
	<object>
		<name>white</name>
		<pose>Unspecified</pose>
		<truncated>0</truncated>
		<difficult>0</difficult>
		<bndbox>
			<xmin>1856</xmin>
			<ymin>871</ymin>
			<xmax>2026</xmax>
			<ymax>1069</ymax>
		</bndbox>
	</object>
	<object>
		<name>white</name>
		<pose>Unspecified</pose>
		<truncated>0</truncated>
		<difficult>0</difficult>
		<bndbox>
			<xmin>2059</xmin>
			<ymin>697</ymin>
			<xmax>2281</xmax>
			<ymax>979</ymax>
		</bndbox>
	</object>
	<object>
		<name>red</name>
		<pose>Unspecified</pose>
		<truncated>0</truncated>
		<difficult>0</difficult>
		<bndbox>
			<xmin>2656</xmin>
			<ymin>264</ymin>
			<xmax>3036</xmax>
			<ymax>784</ymax>
		</bndbox>
	</object>
</annotation>
