<annotation>
	<folder>save</folder>
	<filename>01232.jpg</filename>
	<path>/home/wu/PycharmProjects/hat/save/01232.jpg</path>
	<source>
		<database>Unknown</database>
	</source>
	<size>
		<width>800</width>
		<height>533</height>
		<depth>3</depth>
	</size>
	<segmented>0</segmented>
	<object>
		<name>blue</name>
		<pose>Unspecified</pose>
		<truncated>0</truncated>
		<difficult>0</difficult>
		<bndbox>
			<xmin>193</xmin>
			<ymin>115</ymin>
			<xmax>247</xmax>
			<ymax>188</ymax>
		</bndbox>
	</object>
	<object>
		<name>blue</name>
		<pose>Unspecified</pose>
		<truncated>0</truncated>
		<difficult>0</difficult>
		<bndbox>
			<xmin>318</xmin>
			<ymin>161</ymin>
			<xmax>365</xmax>
			<ymax>220</ymax>
		</bndbox>
	</object>
	<object>
		<name>blue</name>
		<pose>Unspecified</pose>
		<truncated>0</truncated>
		<difficult>0</difficult>
		<bndbox>
			<xmin>585</xmin>
			<ymin>10</ymin>
			<xmax>668</xmax>
			<ymax>109</ymax>
		</bndbox>
	</object>
</annotation>
