<annotation>
	<folder>new822</folder>
	<filename>1492.jpg</filename>
	<path>K:\workstation\data\安全帽\new822\1492.jpg</path>
	<source>
		<database>Unknown</database>
	</source>
	<size>
		<width>490</width>
		<height>367</height>
		<depth>3</depth>
	</size>
	<segmented>0</segmented>
	<object>
		<name>yellow</name>
		<pose>Unspecified</pose>
		<truncated>0</truncated>
		<difficult>0</difficult>
		<bndbox>
			<xmin>23</xmin>
			<ymin>149</ymin>
			<xmax>62</xmax>
			<ymax>201</ymax>
		</bndbox>
	</object>
	<object>
		<name>yellow</name>
		<pose>Unspecified</pose>
		<truncated>0</truncated>
		<difficult>0</difficult>
		<bndbox>
			<xmin>240</xmin>
			<ymin>90</ymin>
			<xmax>259</xmax>
			<ymax>112</ymax>
		</bndbox>
	</object>
	<object>
		<name>yellow</name>
		<pose>Unspecified</pose>
		<truncated>0</truncated>
		<difficult>0</difficult>
		<bndbox>
			<xmin>269</xmin>
			<ymin>98</ymin>
			<xmax>283</xmax>
			<ymax>115</ymax>
		</bndbox>
	</object>
	<object>
		<name>yellow</name>
		<pose>Unspecified</pose>
		<truncated>0</truncated>
		<difficult>0</difficult>
		<bndbox>
			<xmin>265</xmin>
			<ymin>64</ymin>
			<xmax>280</xmax>
			<ymax>81</ymax>
		</bndbox>
	</object>
	<object>
		<name>yellow</name>
		<pose>Unspecified</pose>
		<truncated>0</truncated>
		<difficult>0</difficult>
		<bndbox>
			<xmin>307</xmin>
			<ymin>81</ymin>
			<xmax>325</xmax>
			<ymax>105</ymax>
		</bndbox>
	</object>
	<object>
		<name>yellow</name>
		<pose>Unspecified</pose>
		<truncated>0</truncated>
		<difficult>0</difficult>
		<bndbox>
			<xmin>323</xmin>
			<ymin>80</ymin>
			<xmax>336</xmax>
			<ymax>97</ymax>
		</bndbox>
	</object>
	<object>
		<name>none</name>
		<pose>Unspecified</pose>
		<truncated>0</truncated>
		<difficult>0</difficult>
		<bndbox>
			<xmin>206</xmin>
			<ymin>104</ymin>
			<xmax>228</xmax>
			<ymax>129</ymax>
		</bndbox>
	</object>
	<object>
		<name>none</name>
		<pose>Unspecified</pose>
		<truncated>0</truncated>
		<difficult>0</difficult>
		<bndbox>
			<xmin>105</xmin>
			<ymin>118</ymin>
			<xmax>128</xmax>
			<ymax>148</ymax>
		</bndbox>
	</object>
	<object>
		<name>none</name>
		<pose>Unspecified</pose>
		<truncated>0</truncated>
		<difficult>0</difficult>
		<bndbox>
			<xmin>74</xmin>
			<ymin>111</ymin>
			<xmax>104</xmax>
			<ymax>150</ymax>
		</bndbox>
	</object>
	<object>
		<name>none</name>
		<pose>Unspecified</pose>
		<truncated>0</truncated>
		<difficult>0</difficult>
		<bndbox>
			<xmin>42</xmin>
			<ymin>102</ymin>
			<xmax>73</xmax>
			<ymax>141</ymax>
		</bndbox>
	</object>
</annotation>
