<annotation>
	<folder>new822</folder>
	<filename>1591.jpg</filename>
	<path>K:\workstation\data\安全帽\new822\1591.jpg</path>
	<source>
		<database>Unknown</database>
	</source>
	<size>
		<width>3500</width>
		<height>1932</height>
		<depth>3</depth>
	</size>
	<segmented>0</segmented>
	<object>
		<name>yellow</name>
		<pose>Unspecified</pose>
		<truncated>0</truncated>
		<difficult>0</difficult>
		<bndbox>
			<xmin>780</xmin>
			<ymin>1191</ymin>
			<xmax>854</xmax>
			<ymax>1266</ymax>
		</bndbox>
	</object>
	<object>
		<name>yellow</name>
		<pose>Unspecified</pose>
		<truncated>0</truncated>
		<difficult>0</difficult>
		<bndbox>
			<xmin>1004</xmin>
			<ymin>1143</ymin>
			<xmax>1097</xmax>
			<ymax>1249</ymax>
		</bndbox>
	</object>
	<object>
		<name>yellow</name>
		<pose>Unspecified</pose>
		<truncated>0</truncated>
		<difficult>0</difficult>
		<bndbox>
			<xmin>1102</xmin>
			<ymin>1200</ymin>
			<xmax>1166</xmax>
			<ymax>1275</ymax>
		</bndbox>
	</object>
	<object>
		<name>yellow</name>
		<pose>Unspecified</pose>
		<truncated>0</truncated>
		<difficult>0</difficult>
		<bndbox>
			<xmin>1292</xmin>
			<ymin>1109</ymin>
			<xmax>1367</xmax>
			<ymax>1201</ymax>
		</bndbox>
	</object>
	<object>
		<name>yellow</name>
		<pose>Unspecified</pose>
		<truncated>0</truncated>
		<difficult>0</difficult>
		<bndbox>
			<xmin>1538</xmin>
			<ymin>1138</ymin>
			<xmax>1617</xmax>
			<ymax>1237</ymax>
		</bndbox>
	</object>
	<object>
		<name>yellow</name>
		<pose>Unspecified</pose>
		<truncated>0</truncated>
		<difficult>0</difficult>
		<bndbox>
			<xmin>1790</xmin>
			<ymin>1202</ymin>
			<xmax>1854</xmax>
			<ymax>1276</ymax>
		</bndbox>
	</object>
	<object>
		<name>yellow</name>
		<pose>Unspecified</pose>
		<truncated>0</truncated>
		<difficult>0</difficult>
		<bndbox>
			<xmin>2002</xmin>
			<ymin>1187</ymin>
			<xmax>2076</xmax>
			<ymax>1269</ymax>
		</bndbox>
	</object>
	<object>
		<name>yellow</name>
		<pose>Unspecified</pose>
		<truncated>0</truncated>
		<difficult>0</difficult>
		<bndbox>
			<xmin>2164</xmin>
			<ymin>1173</ymin>
			<xmax>2230</xmax>
			<ymax>1248</ymax>
		</bndbox>
	</object>
	<object>
		<name>yellow</name>
		<pose>Unspecified</pose>
		<truncated>0</truncated>
		<difficult>0</difficult>
		<bndbox>
			<xmin>2382</xmin>
			<ymin>1171</ymin>
			<xmax>2461</xmax>
			<ymax>1253</ymax>
		</bndbox>
	</object>
	<object>
		<name>yellow</name>
		<pose>Unspecified</pose>
		<truncated>0</truncated>
		<difficult>0</difficult>
		<bndbox>
			<xmin>2634</xmin>
			<ymin>1124</ymin>
			<xmax>2726</xmax>
			<ymax>1213</ymax>
		</bndbox>
	</object>
	<object>
		<name>yellow</name>
		<pose>Unspecified</pose>
		<truncated>0</truncated>
		<difficult>0</difficult>
		<bndbox>
			<xmin>3098</xmin>
			<ymin>1148</ymin>
			<xmax>3194</xmax>
			<ymax>1237</ymax>
		</bndbox>
	</object>
</annotation>
