<annotation>
	<folder>saveimage</folder>
	<filename>01681.jpg</filename>
	<path>I:\opencv_projects\cropRegion\saveimage\01681.jpg</path>
	<source>
		<database>Unknown</database>
	</source>
	<size>
		<width>3840</width>
		<height>2561</height>
		<depth>3</depth>
	</size>
	<segmented>0</segmented>
	<object>
		<name>white</name>
		<pose>Unspecified</pose>
		<truncated>0</truncated>
		<difficult>0</difficult>
		<bndbox>
			<xmin>1848</xmin>
			<ymin>1177</ymin>
			<xmax>1908</xmax>
			<ymax>1246</ymax>
		</bndbox>
	</object>
	<object>
		<name>white</name>
		<pose>Unspecified</pose>
		<truncated>0</truncated>
		<difficult>0</difficult>
		<bndbox>
			<xmin>2089</xmin>
			<ymin>1157</ymin>
			<xmax>2137</xmax>
			<ymax>1229</ymax>
		</bndbox>
	</object>
	<object>
		<name>yellow</name>
		<pose>Unspecified</pose>
		<truncated>0</truncated>
		<difficult>0</difficult>
		<bndbox>
			<xmin>1563</xmin>
			<ymin>1571</ymin>
			<xmax>1622</xmax>
			<ymax>1641</ymax>
		</bndbox>
	</object>
	<object>
		<name>yellow</name>
		<pose>Unspecified</pose>
		<truncated>0</truncated>
		<difficult>0</difficult>
		<bndbox>
			<xmin>1106</xmin>
			<ymin>363</ymin>
			<xmax>1151</xmax>
			<ymax>419</ymax>
		</bndbox>
	</object>
</annotation>
