<annotation>
	<folder>saveimage</folder>
	<filename>01943.jpg</filename>
	<path>I:\opencv_projects\cropRegion\saveimage\01943.jpg</path>
	<source>
		<database>Unknown</database>
	</source>
	<size>
		<width>2048</width>
		<height>1536</height>
		<depth>3</depth>
	</size>
	<segmented>0</segmented>
	<object>
		<name>none</name>
		<pose>Unspecified</pose>
		<truncated>0</truncated>
		<difficult>0</difficult>
		<bndbox>
			<xmin>209</xmin>
			<ymin>795</ymin>
			<xmax>307</xmax>
			<ymax>904</ymax>
		</bndbox>
	</object>
	<object>
		<name>none</name>
		<pose>Unspecified</pose>
		<truncated>0</truncated>
		<difficult>0</difficult>
		<bndbox>
			<xmin>483</xmin>
			<ymin>777</ymin>
			<xmax>570</xmax>
			<ymax>882</ymax>
		</bndbox>
	</object>
	<object>
		<name>none</name>
		<pose>Unspecified</pose>
		<truncated>0</truncated>
		<difficult>0</difficult>
		<bndbox>
			<xmin>750</xmin>
			<ymin>788</ymin>
			<xmax>828</xmax>
			<ymax>892</ymax>
		</bndbox>
	</object>
	<object>
		<name>none</name>
		<pose>Unspecified</pose>
		<truncated>0</truncated>
		<difficult>0</difficult>
		<bndbox>
			<xmin>1072</xmin>
			<ymin>856</ymin>
			<xmax>1150</xmax>
			<ymax>953</ymax>
		</bndbox>
	</object>
	<object>
		<name>none</name>
		<pose>Unspecified</pose>
		<truncated>0</truncated>
		<difficult>0</difficult>
		<bndbox>
			<xmin>1235</xmin>
			<ymin>751</ymin>
			<xmax>1301</xmax>
			<ymax>859</ymax>
		</bndbox>
	</object>
	<object>
		<name>none</name>
		<pose>Unspecified</pose>
		<truncated>0</truncated>
		<difficult>0</difficult>
		<bndbox>
			<xmin>1539</xmin>
			<ymin>758</ymin>
			<xmax>1610</xmax>
			<ymax>847</ymax>
		</bndbox>
	</object>
</annotation>
