<annotation>
	<folder>saveimage</folder>
	<filename>02116.jpg</filename>
	<path>I:\opencv_projects\cropRegion\saveimage\02116.jpg</path>
	<source>
		<database>Unknown</database>
	</source>
	<size>
		<width>1023</width>
		<height>683</height>
		<depth>3</depth>
	</size>
	<segmented>0</segmented>
	<object>
		<name>yellow</name>
		<pose>Unspecified</pose>
		<truncated>0</truncated>
		<difficult>0</difficult>
		<bndbox>
			<xmin>417</xmin>
			<ymin>48</ymin>
			<xmax>516</xmax>
			<ymax>160</ymax>
		</bndbox>
	</object>
	<object>
		<name>white</name>
		<pose>Unspecified</pose>
		<truncated>0</truncated>
		<difficult>0</difficult>
		<bndbox>
			<xmin>558</xmin>
			<ymin>161</ymin>
			<xmax>666</xmax>
			<ymax>277</ymax>
		</bndbox>
	</object>
</annotation>
