<annotation>
	<folder>new</folder>
	<filename>02958.jpg</filename>
	<path>/home/wu/PycharmProjects/hat/new/02958.jpg</path>
	<source>
		<database>Unknown</database>
	</source>
	<size>
		<width>1920</width>
		<height>1080</height>
		<depth>3</depth>
	</size>
	<segmented>0</segmented>
	<object>
		<name>yellow</name>
		<pose>Unspecified</pose>
		<truncated>0</truncated>
		<difficult>0</difficult>
		<bndbox>
			<xmin>1042</xmin>
			<ymin>502</ymin>
			<xmax>1071</xmax>
			<ymax>538</ymax>
		</bndbox>
	</object>
	<object>
		<name>yellow</name>
		<pose>Unspecified</pose>
		<truncated>0</truncated>
		<difficult>0</difficult>
		<bndbox>
			<xmin>1034</xmin>
			<ymin>565</ymin>
			<xmax>1067</xmax>
			<ymax>600</ymax>
		</bndbox>
	</object>
	<object>
		<name>white</name>
		<pose>Unspecified</pose>
		<truncated>0</truncated>
		<difficult>0</difficult>
		<bndbox>
			<xmin>1385</xmin>
			<ymin>453</ymin>
			<xmax>1414</xmax>
			<ymax>488</ymax>
		</bndbox>
	</object>
	<object>
		<name>red</name>
		<pose>Unspecified</pose>
		<truncated>0</truncated>
		<difficult>0</difficult>
		<bndbox>
			<xmin>1375</xmin>
			<ymin>426</ymin>
			<xmax>1406</xmax>
			<ymax>459</ymax>
		</bndbox>
	</object>
	<object>
		<name>blue</name>
		<pose>Unspecified</pose>
		<truncated>0</truncated>
		<difficult>0</difficult>
		<bndbox>
			<xmin>1294</xmin>
			<ymin>446</ymin>
			<xmax>1319</xmax>
			<ymax>483</ymax>
		</bndbox>
	</object>
</annotation>
